wacundb.py
wacundb-1.0.1.dist-info/METADATA
wacundb-1.0.1.dist-info/WHEEL
wacundb-1.0.1.dist-info/top_level.txt
wacundb-1.0.1.dist-info/RECORD
